PRProp3D/__init__.py
PRProp3D/model.py
prprop3d-0.3.9.dist-info/licenses/LICENSE
prprop3d-0.3.9.dist-info/METADATA
prprop3d-0.3.9.dist-info/WHEEL
prprop3d-0.3.9.dist-info/top_level.txt
prprop3d-0.3.9.dist-info/RECORD
