Metadata-Version: 2.4
Name: PRProp3D
Version: 0.3.9
Summary: photorefractive propagator for CPU and GPU
Author-email: Mark Cronin-Golomb <mark.croningolomb@gmail.com>
License-Expression: MIT AND (Apache-2.0 OR BSD-2-Clause)
Project-URL: Homepage, https://github.com/mcroning/PRProp3D_package
Requires-Python: >=3.6
License-File: LICENSE
Requires-Dist: scipy>=1.0
Requires-Dist: tqdm
Requires-Dist: matplotlib
Dynamic: license-file
